tests/__init__.py
tests/test_command_managers.py
tests/test_messaging.py
tests/test_subprocess_manager.py
vexbot/__init__.py
vexbot/__main__.py
vexbot/_logging.py
vexbot/_version.py
vexbot/command.py
vexbot/command_observer.py
vexbot/dynamic_entities.py
vexbot/entity_extraction.py
vexbot/extension_metadata.py
vexbot/intents.py
vexbot/language.py
vexbot/messaging.py
vexbot/observer.py
vexbot/robot.py
vexbot/scheduler.py
vexbot/scratch.py
vexbot/subprocess_manager.py
vexbot/adapters/__init__.py
vexbot/adapters/messaging.py
vexbot/adapters/stackoverflow.py
vexbot/adapters/irc/__init__.py
vexbot/adapters/irc/__main__.py
vexbot/adapters/irc/echo_to_message.py
vexbot/adapters/irc/observer.py
vexbot/adapters/shell/__init__.py
vexbot/adapters/shell/__main__.py
vexbot/adapters/shell/completers.py
vexbot/adapters/shell/intents.py
vexbot/adapters/shell/interfaces.py
vexbot/adapters/shell/observers.py
vexbot/adapters/shell/parser.py
vexbot/adapters/shell/shell.py
vexbot/adapters/socket_io/__init__.py
vexbot/adapters/socket_io/__main__.py
vexbot/adapters/socket_io/observer.py
vexbot/adapters/xmpp/__init__.py
vexbot/adapters/xmpp/__main__.py
vexbot/adapters/youtube/__init__.py
vexbot/adapters/youtube/__main__.py
vexbot/extensions/__init__.py
vexbot/extensions/admin.py
vexbot/extensions/develop.py
vexbot/extensions/digitalocean.py
vexbot/extensions/dynamic_loading.py
vexbot/extensions/extensions.py
vexbot/extensions/help.py
vexbot/extensions/hidden.py
vexbot/extensions/intents.py
vexbot/extensions/log.py
vexbot/extensions/modules.py
vexbot/extensions/news.py
vexbot/extensions/subprocess.py
vexbot/extensions/system.py
vexbot/util/__init__.py
vexbot/util/create_cache_filepath.py
vexbot/util/create_config_file.py
vexbot/util/create_vexdir.py
vexbot/util/generate_certificates.py
vexbot/util/generate_config_file.py
vexbot/util/get_cache_filepath.py
vexbot/util/get_certificate_filepath.py
vexbot-0.4.5.dist-info/METADATA
vexbot-0.4.5.dist-info/RECORD
vexbot-0.4.5.dist-info/WHEEL
vexbot-0.4.5.dist-info/entry_points.txt
vexbot-0.4.5.dist-info/top_level.txt
